.gitignore
README.md
setup.py
normalizer/__init__.py
normalizer/core.py
normalizer/normalizer_ml.rules
normalizer.egg-info/PKG-INFO
normalizer.egg-info/SOURCES.txt
normalizer.egg-info/dependency_links.txt
normalizer.egg-info/not-zip-safe
normalizer.egg-info/requires.txt
normalizer.egg-info/top_level.txt