Metadata-Version: 1.0
Name: normalizer
Version: 0.2.1
Summary: Malayalam language normalizer (Experimental)
Home-page: http://silpa.org.in/
Author: Santhosh Thottingal
Author-email: santhosh.thottingal@gmail.com
License: LGPL 3.0
Platform: UNKNOWN
